django_wechat_message-0.0.5.dist-info/DESCRIPTION.rst
django_wechat_message-0.0.5.dist-info/METADATA
django_wechat_message-0.0.5.dist-info/RECORD
django_wechat_message-0.0.5.dist-info/WHEEL
django_wechat_message-0.0.5.dist-info/metadata.json
django_wechat_message-0.0.5.dist-info/top_level.txt
wechat_message/__init__.py
wechat_message/admin.py
wechat_message/api.py
wechat_message/apps.py
wechat_message/models.py
wechat_message/tests.py
wechat_message/urls.py
wechat_message/views.py
wechat_message/locale/zh_Hans/LC_MESSAGES/django.mo
wechat_message/locale/zh_Hans/LC_MESSAGES/django.po
wechat_message/templates/wechat_message/simulator.html
