Metadata-Version: 2.0
Name: django-wechat-message
Version: 0.0.5
Summary: fixed default queryset error, replace get by filter
Home-page: https://github.com/ChanMo/django-wechat-message/
Author: ChanMo
Author-email: chen.orange@aliyun.com
License: BSD License
Keywords: wechat django weixin
Platform: UNKNOWN
Classifier: Environment :: Web Environment
Classifier: Framework :: Django
Classifier: Intended Audience :: Developers
Classifier: License :: OSI Approved :: BSD License
Classifier: Operating System :: OS Independent
Classifier: Programming Language :: Python
Classifier: Programming Language :: Python :: 3
Classifier: Programming Language :: Python :: 3.2
Classifier: Programming Language :: Python :: 3.3
Classifier: Topic :: Internet :: WWW/HTTP
Classifier: Topic :: Internet :: WWW/HTTP :: Dynamic Content
Requires-Dist: django-wechat-base
